<?xml version="1.0" encoding="utf-8"?>
<clothing-items>
 <clothing>
  <id>
   181475733
  </id>
  <name>
   Addidas Dress J-3218
  </name>
  <category>
   Dress
  </category>
  <size>
   S
  </size>
  <color>
   Фиолетовый
  </color>
  <material>
   Шерсть
  </material>
  <price>
   988527
  </price>
  <rating>
   2.9
  </rating>
  <reviews>
   613463
  </reviews>
  <exclusive>
   no
  </exclusive>
 </clothing>
 <clothing>
  <id>
   976144222
  </id>
  <name>
   DC Shirt G-7669
  </name>
  <category>
   Shirt
  </category>
  <size>
   M
  </size>
  <color>
   Красный
  </color>
  <material>
   Кожа
  </material>
  <price>
   935602
  </price>
  <rating>
   4.18
  </rating>
  <reviews>
   682247
  </reviews>
 </clothing>
 <clothing>
  <id>
   863084579
  </id>
  <name>
   Reebok Shoes V-2505
  </name>
  <category>
   Shoes
  </category>
  <size>
   XXL
  </size>
  <color>
   Зеленый
  </color>
  <material>
   Вискоза
  </material>
  <price>
   352793
  </price>
  <rating>
   3.34
  </rating>
  <reviews>
   841792
  </reviews>
  <new>
   -
  </new>
 </clothing>
 <clothing>
  <id>
   113187297
  </id>
  <name>
   Ellesse T-shirt Y-6461
  </name>
  <category>
   T-shirt
  </category>
  <size>
   M
  </size>
  <color>
   Оранжевый
  </color>
  <material>
   Нейлон
  </material>
  <price>
   211146
  </price>
  <rating>
   2.48
  </rating>
  <reviews>
   555938
  </reviews>
  <new>
   -
  </new>
 </clothing>
 <clothing>
  <id>
   435165830
  </id>
  <name>
   DC Hat E-1869
  </name>
  <category>
   Hat
  </category>
  <size>
   XXL
  </size>
  <color>
   Красный
  </color>
  <material>
   Хлопок
  </material>
  <price>
   877508
  </price>
  <rating>
   1.32
  </rating>
  <reviews>
   267970
  </reviews>
 </clothing>
 <clothing>
  <id>
   893090651
  </id>
  <name>
   Asics T-shirt B-8442
  </name>
  <category>
   T-shirt
  </category>
  <size>
   XL
  </size>
  <color>
   Зеленый
  </color>
  <material>
   Лен
  </material>
  <price>
   485436
  </price>
  <rating>
   4.23
  </rating>
  <reviews>
   551300
  </reviews>
  <new>
   -
  </new>
  <exclusive>
   no
  </exclusive>
 </clothing>
 <clothing>
  <id>
   604531730
  </id>
  <name>
   PleinSport Skirt A-8691
  </name>
  <category>
   Skirt
  </category>
  <size>
   XL
  </size>
  <color>
   Желтый
  </color>
  <material>
   Кожа
  </material>
  <price>
   609992
  </price>
  <rating>
   4.58
  </rating>
  <reviews>
   113937
  </reviews>
 </clothing>
 <clothing>
  <id>
   258130909
  </id>
  <name>
   PleinSport Jeans I-8106
  </name>
  <category>
   Jeans
  </category>
  <size>
   M
  </size>
  <color>
   Фиолетовый
  </color>
  <material>
   Кожа
  </material>
  <price>
   482401
  </price>
  <rating>
   3.62
  </rating>
  <reviews>
   285757
  </reviews>
  <new>
   +
  </new>
  <exclusive>
   no
  </exclusive>
 </clothing>
 <clothing>
  <id>
   594652812
  </id>
  <name>
   Puma Dress Z-3640
  </name>
  <category>
   Dress
  </category>
  <size>
   L
  </size>
  <color>
   Синий
  </color>
  <material>
   Вискоза
  </material>
  <price>
   743092
  </price>
  <rating>
   3.97
  </rating>
  <reviews>
   624640
  </reviews>
  <new>
   -
  </new>
 </clothing>
 <clothing>
  <id>
   965569133
  </id>
  <name>
   Fila Belts V-7345
  </name>
  <category>
   Belts
  </category>
  <size>
   L
  </size>
  <color>
   Фиолетовый
  </color>
  <material>
   Хлопок
  </material>
  <price>
   988566
  </price>
  <rating>
   3.38
  </rating>
  <reviews>
   833154
  </reviews>
  <new>
   -
  </new>
  <exclusive>
   yes
  </exclusive>
 </clothing>
 <clothing>
  <id>
   759138984
  </id>
  <name>
   Brooks Dress E-9719
  </name>
  <category>
   Dress
  </category>
  <size>
   S
  </size>
  <color>
   Синий
  </color>
  <material>
   Шелк
  </material>
  <price>
   342518
  </price>
  <rating>
   4.92
  </rating>
  <reviews>
   761763
  </reviews>
  <new>
   -
  </new>
  <sporty>
   yes
  </sporty>
 </clothing>
 <clothing>
  <id>
   163328423
  </id>
  <name>
   PleinSport Jacket W-3520
  </name>
  <category>
   Jacket
  </category>
  <size>
   L
  </size>
  <color>
   Фиолетовый
  </color>
  <material>
   Шерсть
  </material>
  <price>
   520489
  </price>
  <rating>
   1.23
  </rating>
  <reviews>
   772659
  </reviews>
  <exclusive>
   no
  </exclusive>
  <sporty>
   yes
  </sporty>
 </clothing>
 <clothing>
  <id>
   974500665
  </id>
  <name>
   Nike Skirt C-1098
  </name>
  <category>
   Skirt
  </category>
  <size>
   S
  </size>
  <color>
   Синий
  </color>
  <material>
   Кожа
  </material>
  <price>
   338810
  </price>
  <rating>
   2.96
  </rating>
  <reviews>
   821869
  </reviews>
  <exclusive>
   yes
  </exclusive>
  <sporty>
   yes
  </sporty>
 </clothing>
 <clothing>
  <id>
   101314320
  </id>
  <name>
   Under Armour Blouse P-5689
  </name>
  <category>
   Blouse
  </category>
  <size>
   L
  </size>
  <color>
   Оранжевый
  </color>
  <material>
   Шелк
  </material>
  <price>
   589596
  </price>
  <rating>
   2.9
  </rating>
  <reviews>
   143340
  </reviews>
  <sporty>
   yes
  </sporty>
 </clothing>
</clothing-items>
