<?xml version="1.0" encoding="utf-8"?>
<clothing-items>
 <clothing>
  <id>
   165938264
  </id>
  <name>
   Nike Jacket P-5362
  </name>
  <category>
   Jacket
  </category>
  <size>
   S
  </size>
  <color>
   Красный
  </color>
  <material>
   Полиэстер
  </material>
  <price>
   416861
  </price>
  <rating>
   4.88
  </rating>
  <reviews>
   197536
  </reviews>
  <new>
   +
  </new>
  <sporty>
   yes
  </sporty>
 </clothing>
 <clothing>
  <id>
   594984341
  </id>
  <name>
   Fila Socks T-5619
  </name>
  <category>
   Socks
  </category>
  <size>
   XL
  </size>
  <color>
   Зеленый
  </color>
  <material>
   Полиэстер
  </material>
  <price>
   149347
  </price>
  <rating>
   1.67
  </rating>
  <reviews>
   748821
  </reviews>
  <exclusive>
   yes
  </exclusive>
  <sporty>
   yes
  </sporty>
 </clothing>
 <clothing>
  <id>
   345316413
  </id>
  <name>
   Fila Blouse S-2717
  </name>
  <category>
   Blouse
  </category>
  <size>
   XL
  </size>
  <color>
   Голубой
  </color>
  <material>
   Полиэстер
  </material>
  <price>
   632091
  </price>
  <rating>
   1.33
  </rating>
  <reviews>
   659694
  </reviews>
  <sporty>
   no
  </sporty>
 </clothing>
 <clothing>
  <id>
   117555489
  </id>
  <name>
   Fila Hat A-4717
  </name>
  <category>
   Hat
  </category>
  <size>
   L
  </size>
  <color>
   Желтый
  </color>
  <material>
   Кожа
  </material>
  <price>
   286254
  </price>
  <rating>
   4.55
  </rating>
  <reviews>
   588776
  </reviews>
  <exclusive>
   yes
  </exclusive>
  <sporty>
   yes
  </sporty>
 </clothing>
 <clothing>
  <id>
   650556449
  </id>
  <name>
   Under Armour Skirt I-5104
  </name>
  <category>
   Skirt
  </category>
  <size>
   XL
  </size>
  <color>
   Красный
  </color>
  <material>
   Кожа
  </material>
  <price>
   950603
  </price>
  <rating>
   3.25
  </rating>
  <reviews>
   976473
  </reviews>
  <new>
   -
  </new>
  <exclusive>
   no
  </exclusive>
 </clothing>
 <clothing>
  <id>
   176568121
  </id>
  <name>
   Brooks Hat Z-9519
  </name>
  <category>
   Hat
  </category>
  <size>
   L
  </size>
  <color>
   Голубой
  </color>
  <material>
   Лен
  </material>
  <price>
   423500
  </price>
  <rating>
   1.63
  </rating>
  <reviews>
   715218
  </reviews>
  <new>
   -
  </new>
  <sporty>
   no
  </sporty>
 </clothing>
 <clothing>
  <id>
   329353672
  </id>
  <name>
   Adidas Gloves X-5878
  </name>
  <category>
   Gloves
  </category>
  <size>
   L
  </size>
  <color>
   Зеленый
  </color>
  <material>
   Кожа
  </material>
  <price>
   924254
  </price>
  <rating>
   3.88
  </rating>
  <reviews>
   551798
  </reviews>
  <exclusive>
   yes
  </exclusive>
 </clothing>
 <clothing>
  <id>
   722260983
  </id>
  <name>
   Adidas Umbrellas M-2320
  </name>
  <category>
   Umbrellas
  </category>
  <size>
   XL
  </size>
  <color>
   Фиолетовый
  </color>
  <material>
   Нейлон
  </material>
  <price>
   442398
  </price>
  <rating>
   1.4
  </rating>
  <reviews>
   238798
  </reviews>
 </clothing>
 <clothing>
  <id>
   873824472
  </id>
  <name>
   Asics Handbags R-5023
  </name>
  <category>
   Handbags
  </category>
  <size>
   XL
  </size>
  <color>
   Оранжевый
  </color>
  <material>
   Лен
  </material>
  <price>
   748467
  </price>
  <rating>
   2.67
  </rating>
  <reviews>
   696097
  </reviews>
  <sporty>
   yes
  </sporty>
 </clothing>
 <clothing>
  <id>
   190758557
  </id>
  <name>
   PleinSport Gloves A-3123
  </name>
  <category>
   Gloves
  </category>
  <size>
   XXL
  </size>
  <color>
   Красный
  </color>
  <material>
   Вискоза
  </material>
  <price>
   927633
  </price>
  <rating>
   3.64
  </rating>
  <reviews>
   468877
  </reviews>
  <new>
   -
  </new>
  <exclusive>
   no
  </exclusive>
  <sporty>
   no
  </sporty>
 </clothing>
 <clothing>
  <id>
   866072938
  </id>
  <name>
   Vans Hat X-2976
  </name>
  <category>
   Hat
  </category>
  <size>
   L
  </size>
  <color>
   Синий
  </color>
  <material>
   Шерсть
  </material>
  <price>
   641954
  </price>
  <rating>
   3.03
  </rating>
  <reviews>
   336783
  </reviews>
  <new>
   -
  </new>
  <sporty>
   no
  </sporty>
 </clothing>
 <clothing>
  <id>
   129136681
  </id>
  <name>
   Lacoste Jeans Q-9198
  </name>
  <category>
   Jeans
  </category>
  <size>
   M
  </size>
  <color>
   Синий
  </color>
  <material>
   Кожа
  </material>
  <price>
   812703
  </price>
  <rating>
   1.51
  </rating>
  <reviews>
   697923
  </reviews>
  <exclusive>
   yes
  </exclusive>
 </clothing>
 <clothing>
  <id>
   559915541
  </id>
  <name>
   Brooks Dress B-6885
  </name>
  <category>
   Dress
  </category>
  <size>
   M
  </size>
  <color>
   Красный
  </color>
  <material>
   Кожа
  </material>
  <price>
   790267
  </price>
  <rating>
   4.04
  </rating>
  <reviews>
   906388
  </reviews>
 </clothing>
 <clothing>
  <id>
   858743969
  </id>
  <name>
   PleinSport T-shirt L-3412
  </name>
  <category>
   T-shirt
  </category>
  <size>
   XL
  </size>
  <color>
   Синий
  </color>
  <material>
   Нейлон
  </material>
  <price>
   428939
  </price>
  <rating>
   4.17
  </rating>
  <reviews>
   48802
  </reviews>
  <exclusive>
   no
  </exclusive>
  <sporty>
   no
  </sporty>
 </clothing>
 <clothing>
  <id>
   719224162
  </id>
  <name>
   Adidas Shoes C-7481
  </name>
  <category>
   Shoes
  </category>
  <size>
   S
  </size>
  <color>
   Фиолетовый
  </color>
  <material>
   Нейлон
  </material>
  <price>
   418141
  </price>
  <rating>
   3.79
  </rating>
  <reviews>
   323638
  </reviews>
  <exclusive>
   no
  </exclusive>
  <sporty>
   yes
  </sporty>
 </clothing>
 <clothing>
  <id>
   431535511
  </id>
  <name>
   Vans Umbrellas L-2901
  </name>
  <category>
   Umbrellas
  </category>
  <size>
   S
  </size>
  <color>
   Красный
  </color>
  <material>
   Шерсть
  </material>
  <price>
   495998
  </price>
  <rating>
   3.22
  </rating>
  <reviews>
   776119
  </reviews>
  <sporty>
   no
  </sporty>
 </clothing>
 <clothing>
  <id>
   456741554
  </id>
  <name>
   Lacoste Shirt Y-3471
  </name>
  <category>
   Shirt
  </category>
  <size>
   XXL
  </size>
  <color>
   Синий
  </color>
  <material>
   Полиэстер
  </material>
  <price>
   683894
  </price>
  <rating>
   4.08
  </rating>
  <reviews>
   341191
  </reviews>
  <sporty>
   no
  </sporty>
 </clothing>
 <clothing>
  <id>
   569892074
  </id>
  <name>
   Puma Shirt N-8942
  </name>
  <category>
   Shirt
  </category>
  <size>
   M
  </size>
  <color>
   Желтый
  </color>
  <material>
   Вискоза
  </material>
  <price>
   728398
  </price>
  <rating>
   2.13
  </rating>
  <reviews>
   624478
  </reviews>
  <sporty>
   no
  </sporty>
 </clothing>
 <clothing>
  <id>
   595672816
  </id>
  <name>
   Lacoste Sweater H-7848
  </name>
  <category>
   Sweater
  </category>
  <size>
   M
  </size>
  <color>
   Красный
  </color>
  <material>
   Шерсть
  </material>
  <price>
   320868
  </price>
  <rating>
   2.06
  </rating>
  <reviews>
   337562
  </reviews>
  <new>
   +
  </new>
  <exclusive>
   yes
  </exclusive>
  <sporty>
   yes
  </sporty>
 </clothing>
 <clothing>
  <id>
   835984818
  </id>
  <name>
   Puma Blouse Y-2730
  </name>
  <category>
   Blouse
  </category>
  <size>
   S
  </size>
  <color>
   Синий
  </color>
  <material>
   Нейлон
  </material>
  <price>
   189475
  </price>
  <rating>
   4.89
  </rating>
  <reviews>
   476868
  </reviews>
  <exclusive>
   yes
  </exclusive>
 </clothing>
 <clothing>
  <id>
   662389843
  </id>
  <name>
   Puma Pants P-2385
  </name>
  <category>
   Pants
  </category>
  <size>
   XL
  </size>
  <color>
   Красный
  </color>
  <material>
   Полиэстер
  </material>
  <price>
   107264
  </price>
  <rating>
   1.01
  </rating>
  <reviews>
   18381
  </reviews>
  <exclusive>
   no
  </exclusive>
  <sporty>
   no
  </sporty>
 </clothing>
 <clothing>
  <id>
   967609842
  </id>
  <name>
   Under Armour Gloves I-8593
  </name>
  <category>
   Gloves
  </category>
  <size>
   S
  </size>
  <color>
   Желтый
  </color>
  <material>
   Полиэстер
  </material>
  <price>
   679563
  </price>
  <rating>
   1.29
  </rating>
  <reviews>
   613706
  </reviews>
  <new>
   +
  </new>
  <exclusive>
   no
  </exclusive>
 </clothing>
 <clothing>
  <id>
   666376694
  </id>
  <name>
   Puma Pants G-5091
  </name>
  <category>
   Pants
  </category>
  <size>
   M
  </size>
  <color>
   Голубой
  </color>
  <material>
   Шерсть
  </material>
  <price>
   574263
  </price>
  <rating>
   3.44
  </rating>
  <reviews>
   732300
  </reviews>
  <new>
   +
  </new>
 </clothing>
 <clothing>
  <id>
   418139567
  </id>
  <name>
   PleinSport Pants A-7473
  </name>
  <category>
   Pants
  </category>
  <size>
   XXL
  </size>
  <color>
   Голубой
  </color>
  <material>
   Полиэстер
  </material>
  <price>
   915333
  </price>
  <rating>
   2.12
  </rating>
  <reviews>
   758562
  </reviews>
  <new>
   -
  </new>
  <exclusive>
   no
  </exclusive>
  <sporty>
   yes
  </sporty>
 </clothing>
 <clothing>
  <id>
   282440190
  </id>
  <name>
   Puma Dress Z-4899
  </name>
  <category>
   Dress
  </category>
  <size>
   XXL
  </size>
  <color>
   Голубой
  </color>
  <material>
   Нейлон
  </material>
  <price>
   456162
  </price>
  <rating>
   4.61
  </rating>
  <reviews>
   839364
  </reviews>
  <new>
   +
  </new>
 </clothing>
 <clothing>
  <id>
   368355484
  </id>
  <name>
   DC Shoes R-9033
  </name>
  <category>
   Shoes
  </category>
  <size>
   XL
  </size>
  <color>
   Желтый
  </color>
  <material>
   Вискоза
  </material>
  <price>
   334968
  </price>
  <rating>
   4.34
  </rating>
  <reviews>
   152888
  </reviews>
  <new>
   -
  </new>
  <exclusive>
   yes
  </exclusive>
 </clothing>
 <clothing>
  <id>
   604436320
  </id>
  <name>
   Asics Gloves C-7340
  </name>
  <category>
   Gloves
  </category>
  <size>
   M
  </size>
  <color>
   Голубой
  </color>
  <material>
   Полиэстер
  </material>
  <price>
   112392
  </price>
  <rating>
   3.15
  </rating>
  <reviews>
   101677
  </reviews>
  <sporty>
   yes
  </sporty>
 </clothing>
 <clothing>
  <id>
   328739887
  </id>
  <name>
   Converse Blouse Q-2015
  </name>
  <category>
   Blouse
  </category>
  <size>
   L
  </size>
  <color>
   Желтый
  </color>
  <material>
   Шелк
  </material>
  <price>
   161227
  </price>
  <rating>
   3.96
  </rating>
  <reviews>
   970731
  </reviews>
  <new>
   +
  </new>
  <exclusive>
   no
  </exclusive>
  <sporty>
   yes
  </sporty>
 </clothing>
 <clothing>
  <id>
   810930069
  </id>
  <name>
   Under Armour Umbrellas F-4408
  </name>
  <category>
   Umbrellas
  </category>
  <size>
   XXL
  </size>
  <color>
   Оранжевый
  </color>
  <material>
   Лен
  </material>
  <price>
   548812
  </price>
  <rating>
   3.69
  </rating>
  <reviews>
   637662
  </reviews>
  <new>
   -
  </new>
  <exclusive>
   yes
  </exclusive>
  <sporty>
   no
  </sporty>
 </clothing>
 <clothing>
  <id>
   396175145
  </id>
  <name>
   Ellesse Jacket I-2588
  </name>
  <category>
   Jacket
  </category>
  <size>
   L
  </size>
  <color>
   Синий
  </color>
  <material>
   Полиэстер
  </material>
  <price>
   982668
  </price>
  <rating>
   4.55
  </rating>
  <reviews>
   331395
  </reviews>
  <exclusive>
   yes
  </exclusive>
 </clothing>
 <clothing>
  <id>
   522685523
  </id>
  <name>
   Nike Gloves S-1079
  </name>
  <category>
   Gloves
  </category>
  <size>
   XL
  </size>
  <color>
   Оранжевый
  </color>
  <material>
   Нейлон
  </material>
  <price>
   441113
  </price>
  <rating>
   2.95
  </rating>
  <reviews>
   550247
  </reviews>
  <exclusive>
   yes
  </exclusive>
 </clothing>
 <clothing>
  <id>
   606786207
  </id>
  <name>
   DC Umbrellas Z-4447
  </name>
  <category>
   Umbrellas
  </category>
  <size>
   L
  </size>
  <color>
   Оранжевый
  </color>
  <material>
   Лен
  </material>
  <price>
   108696
  </price>
  <rating>
   2.9
  </rating>
  <reviews>
   592970
  </reviews>
  <new>
   -
  </new>
  <exclusive>
   no
  </exclusive>
  <sporty>
   no
  </sporty>
 </clothing>
 <clothing>
  <id>
   399281978
  </id>
  <name>
   Adidas Umbrellas B-4086
  </name>
  <category>
   Umbrellas
  </category>
  <size>
   XXL
  </size>
  <color>
   Красный
  </color>
  <material>
   Кожа
  </material>
  <price>
   993559
  </price>
  <rating>
   2.31
  </rating>
  <reviews>
   906983
  </reviews>
 </clothing>
 <clothing>
  <id>
   206746219
  </id>
  <name>
   Puma Shoes P-8227
  </name>
  <category>
   Shoes
  </category>
  <size>
   L
  </size>
  <color>
   Фиолетовый
  </color>
  <material>
   Шелк
  </material>
  <price>
   770477
  </price>
  <rating>
   3.18
  </rating>
  <reviews>
   433688
  </reviews>
  <exclusive>
   no
  </exclusive>
  <sporty>
   no
  </sporty>
 </clothing>
 <clothing>
  <id>
   742626762
  </id>
  <name>
   Converse Shoes P-3992
  </name>
  <category>
   Shoes
  </category>
  <size>
   XL
  </size>
  <color>
   Оранжевый
  </color>
  <material>
   Вискоза
  </material>
  <price>
   323082
  </price>
  <rating>
   2.32
  </rating>
  <reviews>
   393068
  </reviews>
  <new>
   -
  </new>
  <exclusive>
   no
  </exclusive>
 </clothing>
 <clothing>
  <id>
   403837965
  </id>
  <name>
   Brooks Blouse U-9651
  </name>
  <category>
   Blouse
  </category>
  <size>
   S
  </size>
  <color>
   Красный
  </color>
  <material>
   Шелк
  </material>
  <price>
   810782
  </price>
  <rating>
   2.75
  </rating>
  <reviews>
   643211
  </reviews>
  <exclusive>
   no
  </exclusive>
 </clothing>
 <clothing>
  <id>
   985046343
  </id>
  <name>
   Addidas Gloves I-3814
  </name>
  <category>
   Gloves
  </category>
  <size>
   M
  </size>
  <color>
   Синий
  </color>
  <material>
   Кожа
  </material>
  <price>
   568067
  </price>
  <rating>
   2.84
  </rating>
  <reviews>
   388514
  </reviews>
  <exclusive>
   no
  </exclusive>
  <sporty>
   no
  </sporty>
 </clothing>
 <clothing>
  <id>
   645228758
  </id>
  <name>
   Ellesse Gloves T-3746
  </name>
  <category>
   Gloves
  </category>
  <size>
   XXL
  </size>
  <color>
   Желтый
  </color>
  <material>
   Полиэстер
  </material>
  <price>
   235970
  </price>
  <rating>
   3.6
  </rating>
  <reviews>
   904112
  </reviews>
  <new>
   -
  </new>
  <exclusive>
   no
  </exclusive>
  <sporty>
   no
  </sporty>
 </clothing>
 <clothing>
  <id>
   893413932
  </id>
  <name>
   Asics Shirt S-7797
  </name>
  <category>
   Shirt
  </category>
  <size>
   XL
  </size>
  <color>
   Фиолетовый
  </color>
  <material>
   Шелк
  </material>
  <price>
   922990
  </price>
  <rating>
   1.44
  </rating>
  <reviews>
   131504
  </reviews>
  <new>
   -
  </new>
  <exclusive>
   no
  </exclusive>
  <sporty>
   yes
  </sporty>
 </clothing>
 <clothing>
  <id>
   375475543
  </id>
  <name>
   Reebok Pants D-7940
  </name>
  <category>
   Pants
  </category>
  <size>
   XXL
  </size>
  <color>
   Фиолетовый
  </color>
  <material>
   Вискоза
  </material>
  <price>
   777306
  </price>
  <rating>
   4.74
  </rating>
  <reviews>
   306669
  </reviews>
  <exclusive>
   no
  </exclusive>
  <sporty>
   no
  </sporty>
 </clothing>
 <clothing>
  <id>
   196998093
  </id>
  <name>
   DC Shirt G-3377
  </name>
  <category>
   Shirt
  </category>
  <size>
   XXL
  </size>
  <color>
   Красный
  </color>
  <material>
   Вискоза
  </material>
  <price>
   204939
  </price>
  <rating>
   4.86
  </rating>
  <reviews>
   966582
  </reviews>
  <sporty>
   no
  </sporty>
 </clothing>
 <clothing>
  <id>
   586405852
  </id>
  <name>
   Vans Skirt Q-2776
  </name>
  <category>
   Skirt
  </category>
  <size>
   M
  </size>
  <color>
   Фиолетовый
  </color>
  <material>
   Лен
  </material>
  <price>
   568515
  </price>
  <rating>
   3.67
  </rating>
  <reviews>
   28046
  </reviews>
  <new>
   -
  </new>
 </clothing>
 <clothing>
  <id>
   456619771
  </id>
  <name>
   Lacoste Pants J-2424
  </name>
  <category>
   Pants
  </category>
  <size>
   S
  </size>
  <color>
   Оранжевый
  </color>
  <material>
   Нейлон
  </material>
  <price>
   319788
  </price>
  <rating>
   2.61
  </rating>
  <reviews>
   261589
  </reviews>
  <exclusive>
   yes
  </exclusive>
  <sporty>
   yes
  </sporty>
 </clothing>
 <clothing>
  <id>
   272464913
  </id>
  <name>
   Under Armour Jacket M-9816
  </name>
  <category>
   Jacket
  </category>
  <size>
   M
  </size>
  <color>
   Желтый
  </color>
  <material>
   Шерсть
  </material>
  <price>
   178509
  </price>
  <rating>
   1.62
  </rating>
  <reviews>
   89214
  </reviews>
  <exclusive>
   no
  </exclusive>
  <sporty>
   no
  </sporty>
 </clothing>
 <clothing>
  <id>
   742953886
  </id>
  <name>
   Reebok Dress H-7837
  </name>
  <category>
   Dress
  </category>
  <size>
   XXL
  </size>
  <color>
   Желтый
  </color>
  <material>
   Кожа
  </material>
  <price>
   620789
  </price>
  <rating>
   2.91
  </rating>
  <reviews>
   67980
  </reviews>
  <exclusive>
   no
  </exclusive>
  <sporty>
   no
  </sporty>
 </clothing>
 <clothing>
  <id>
   484901215
  </id>
  <name>
   DC Skirt K-9045
  </name>
  <category>
   Skirt
  </category>
  <size>
   S
  </size>
  <color>
   Фиолетовый
  </color>
  <material>
   Шелк
  </material>
  <price>
   891364
  </price>
  <rating>
   2.65
  </rating>
  <reviews>
   236692
  </reviews>
  <new>
   -
  </new>
  <sporty>
   yes
  </sporty>
 </clothing>
 <clothing>
  <id>
   721294961
  </id>
  <name>
   Brooks Jacket N-3873
  </name>
  <category>
   Jacket
  </category>
  <size>
   XL
  </size>
  <color>
   Оранжевый
  </color>
  <material>
   Лен
  </material>
  <price>
   319895
  </price>
  <rating>
   1.94
  </rating>
  <reviews>
   469118
  </reviews>
  <new>
   -
  </new>
  <exclusive>
   no
  </exclusive>
  <sporty>
   no
  </sporty>
 </clothing>
 <clothing>
  <id>
   101099207
  </id>
  <name>
   PleinSport Umbrellas L-4996
  </name>
  <category>
   Umbrellas
  </category>
  <size>
   XL
  </size>
  <color>
   Зеленый
  </color>
  <material>
   Вискоза
  </material>
  <price>
   589184
  </price>
  <rating>
   2.98
  </rating>
  <reviews>
   836732
  </reviews>
  <new>
   -
  </new>
  <exclusive>
   no
  </exclusive>
  <sporty>
   yes
  </sporty>
 </clothing>
 <clothing>
  <id>
   611658036
  </id>
  <name>
   DC Socks G-9895
  </name>
  <category>
   Socks
  </category>
  <size>
   S
  </size>
  <color>
   Синий
  </color>
  <material>
   Шерсть
  </material>
  <price>
   712585
  </price>
  <rating>
   1.51
  </rating>
  <reviews>
   459812
  </reviews>
  <new>
   +
  </new>
  <exclusive>
   yes
  </exclusive>
  <sporty>
   no
  </sporty>
 </clothing>
</clothing-items>
