<?xml version="1.0" encoding="utf-8"?>
<clothing-items>
 <clothing>
  <id>
   745461212
  </id>
  <name>
   Addidas Skirt L-7147
  </name>
  <category>
   Skirt
  </category>
  <size>
   XL
  </size>
  <color>
   Фиолетовый
  </color>
  <material>
   Полиэстер
  </material>
  <price>
   298688
  </price>
  <rating>
   4.04
  </rating>
  <reviews>
   765194
  </reviews>
  <sporty>
   no
  </sporty>
 </clothing>
 <clothing>
  <id>
   317339303
  </id>
  <name>
   Under Armour Jeans A-8067
  </name>
  <category>
   Jeans
  </category>
  <size>
   XXL
  </size>
  <color>
   Красный
  </color>
  <material>
   Полиэстер
  </material>
  <price>
   544903
  </price>
  <rating>
   2.11
  </rating>
  <reviews>
   489437
  </reviews>
  <sporty>
   yes
  </sporty>
 </clothing>
 <clothing>
  <id>
   672709346
  </id>
  <name>
   Converse Hat V-4154
  </name>
  <category>
   Hat
  </category>
  <size>
   L
  </size>
  <color>
   Фиолетовый
  </color>
  <material>
   Хлопок
  </material>
  <price>
   540436
  </price>
  <rating>
   3.75
  </rating>
  <reviews>
   873711
  </reviews>
  <new>
   +
  </new>
 </clothing>
 <clothing>
  <id>
   614693673
  </id>
  <name>
   Brooks Hat J-6484
  </name>
  <category>
   Hat
  </category>
  <size>
   M
  </size>
  <color>
   Фиолетовый
  </color>
  <material>
   Вискоза
  </material>
  <price>
   311666
  </price>
  <rating>
   1.21
  </rating>
  <reviews>
   54743
  </reviews>
  <exclusive>
   no
  </exclusive>
  <sporty>
   no
  </sporty>
 </clothing>
 <clothing>
  <id>
   590785890
  </id>
  <name>
   Asics Belts W-2046
  </name>
  <category>
   Belts
  </category>
  <size>
   XL
  </size>
  <color>
   Зеленый
  </color>
  <material>
   Хлопок
  </material>
  <price>
   775384
  </price>
  <rating>
   2.72
  </rating>
  <reviews>
   557396
  </reviews>
  <exclusive>
   yes
  </exclusive>
 </clothing>
 <clothing>
  <id>
   597191978
  </id>
  <name>
   Ellesse Skirt G-7313
  </name>
  <category>
   Skirt
  </category>
  <size>
   XL
  </size>
  <color>
   Голубой
  </color>
  <material>
   Нейлон
  </material>
  <price>
   831755
  </price>
  <rating>
   3.49
  </rating>
  <reviews>
   830408
  </reviews>
  <new>
   -
  </new>
  <exclusive>
   no
  </exclusive>
 </clothing>
 <clothing>
  <id>
   562902025
  </id>
  <name>
   PleinSport Dress G-7858
  </name>
  <category>
   Dress
  </category>
  <size>
   M
  </size>
  <color>
   Красный
  </color>
  <material>
   Полиэстер
  </material>
  <price>
   845252
  </price>
  <rating>
   3.0
  </rating>
  <reviews>
   122932
  </reviews>
  <new>
   +
  </new>
  <sporty>
   yes
  </sporty>
 </clothing>
 <clothing>
  <id>
   989006870
  </id>
  <name>
   Addidas Umbrellas H-7868
  </name>
  <category>
   Umbrellas
  </category>
  <size>
   L
  </size>
  <color>
   Фиолетовый
  </color>
  <material>
   Полиэстер
  </material>
  <price>
   323158
  </price>
  <rating>
   2.85
  </rating>
  <reviews>
   516694
  </reviews>
  <exclusive>
   yes
  </exclusive>
  <sporty>
   no
  </sporty>
 </clothing>
 <clothing>
  <id>
   505025591
  </id>
  <name>
   Reebok Socks Z-8784
  </name>
  <category>
   Socks
  </category>
  <size>
   M
  </size>
  <color>
   Синий
  </color>
  <material>
   Вискоза
  </material>
  <price>
   464649
  </price>
  <rating>
   1.94
  </rating>
  <reviews>
   488791
  </reviews>
  <sporty>
   no
  </sporty>
 </clothing>
 <clothing>
  <id>
   122682236
  </id>
  <name>
   Reebok Shirt I-4602
  </name>
  <category>
   Shirt
  </category>
  <size>
   XL
  </size>
  <color>
   Красный
  </color>
  <material>
   Вискоза
  </material>
  <price>
   982221
  </price>
  <rating>
   2.38
  </rating>
  <reviews>
   160507
  </reviews>
  <new>
   -
  </new>
  <exclusive>
   no
  </exclusive>
  <sporty>
   no
  </sporty>
 </clothing>
 <clothing>
  <id>
   645584359
  </id>
  <name>
   Vans Belts N-9391
  </name>
  <category>
   Belts
  </category>
  <size>
   XXL
  </size>
  <color>
   Красный
  </color>
  <material>
   Шерсть
  </material>
  <price>
   605175
  </price>
  <rating>
   3.06
  </rating>
  <reviews>
   348985
  </reviews>
  <new>
   -
  </new>
  <sporty>
   yes
  </sporty>
 </clothing>
 <clothing>
  <id>
   283396862
  </id>
  <name>
   Asics Gloves U-8309
  </name>
  <category>
   Gloves
  </category>
  <size>
   L
  </size>
  <color>
   Голубой
  </color>
  <material>
   Шерсть
  </material>
  <price>
   772916
  </price>
  <rating>
   3.08
  </rating>
  <reviews>
   403583
  </reviews>
  <exclusive>
   no
  </exclusive>
 </clothing>
 <clothing>
  <id>
   254066828
  </id>
  <name>
   Lacoste Shirt L-3756
  </name>
  <category>
   Shirt
  </category>
  <size>
   S
  </size>
  <color>
   Желтый
  </color>
  <material>
   Кожа
  </material>
  <price>
   353071
  </price>
  <rating>
   4.84
  </rating>
  <reviews>
   179077
  </reviews>
  <new>
   -
  </new>
 </clothing>
 <clothing>
  <id>
   464763515
  </id>
  <name>
   New Balance Pants E-4747
  </name>
  <category>
   Pants
  </category>
  <size>
   M
  </size>
  <color>
   Красный
  </color>
  <material>
   Шелк
  </material>
  <price>
   192426
  </price>
  <rating>
   4.15
  </rating>
  <reviews>
   763960
  </reviews>
  <new>
   +
  </new>
 </clothing>
 <clothing>
  <id>
   893488872
  </id>
  <name>
   Nike Dress C-7194
  </name>
  <category>
   Dress
  </category>
  <size>
   M
  </size>
  <color>
   Желтый
  </color>
  <material>
   Вискоза
  </material>
  <price>
   938983
  </price>
  <rating>
   4.06
  </rating>
  <reviews>
   122655
  </reviews>
  <new>
   +
  </new>
  <sporty>
   no
  </sporty>
 </clothing>
 <clothing>
  <id>
   884287276
  </id>
  <name>
   Adidas Gloves G-9144
  </name>
  <category>
   Gloves
  </category>
  <size>
   S
  </size>
  <color>
   Синий
  </color>
  <material>
   Шелк
  </material>
  <price>
   944724
  </price>
  <rating>
   4.52
  </rating>
  <reviews>
   168146
  </reviews>
  <new>
   +
  </new>
  <exclusive>
   yes
  </exclusive>
  <sporty>
   yes
  </sporty>
 </clothing>
 <clothing>
  <id>
   560250179
  </id>
  <name>
   Fila Skirt N-1373
  </name>
  <category>
   Skirt
  </category>
  <size>
   XL
  </size>
  <color>
   Желтый
  </color>
  <material>
   Шерсть
  </material>
  <price>
   809964
  </price>
  <rating>
   3.27
  </rating>
  <reviews>
   835030
  </reviews>
  <new>
   -
  </new>
 </clothing>
 <clothing>
  <id>
   356302011
  </id>
  <name>
   DC Pants U-5199
  </name>
  <category>
   Pants
  </category>
  <size>
   L
  </size>
  <color>
   Синий
  </color>
  <material>
   Хлопок
  </material>
  <price>
   924276
  </price>
  <rating>
   1.15
  </rating>
  <reviews>
   796329
  </reviews>
  <sporty>
   yes
  </sporty>
 </clothing>
 <clothing>
  <id>
   142044134
  </id>
  <name>
   Fila Hat D-7824
  </name>
  <category>
   Hat
  </category>
  <size>
   XL
  </size>
  <color>
   Желтый
  </color>
  <material>
   Хлопок
  </material>
  <price>
   541046
  </price>
  <rating>
   1.37
  </rating>
  <reviews>
   160622
  </reviews>
  <sporty>
   no
  </sporty>
 </clothing>
 <clothing>
  <id>
   330037123
  </id>
  <name>
   Brooks Jacket L-8196
  </name>
  <category>
   Jacket
  </category>
  <size>
   XL
  </size>
  <color>
   Красный
  </color>
  <material>
   Полиэстер
  </material>
  <price>
   209897
  </price>
  <rating>
   4.24
  </rating>
  <reviews>
   274859
  </reviews>
  <sporty>
   yes
  </sporty>
 </clothing>
 <clothing>
  <id>
   734567522
  </id>
  <name>
   Ellesse Socks H-7223
  </name>
  <category>
   Socks
  </category>
  <size>
   M
  </size>
  <color>
   Зеленый
  </color>
  <material>
   Нейлон
  </material>
  <price>
   817826
  </price>
  <rating>
   2.23
  </rating>
  <reviews>
   820860
  </reviews>
  <exclusive>
   no
  </exclusive>
  <sporty>
   no
  </sporty>
 </clothing>
 <clothing>
  <id>
   315595923
  </id>
  <name>
   Adidas T-shirt L-6370
  </name>
  <category>
   T-shirt
  </category>
  <size>
   S
  </size>
  <color>
   Фиолетовый
  </color>
  <material>
   Хлопок
  </material>
  <price>
   187191
  </price>
  <rating>
   3.6
  </rating>
  <reviews>
   891053
  </reviews>
  <new>
   -
  </new>
  <exclusive>
   no
  </exclusive>
 </clothing>
 <clothing>
  <id>
   290278409
  </id>
  <name>
   Adidas Socks P-1984
  </name>
  <category>
   Socks
  </category>
  <size>
   XL
  </size>
  <color>
   Зеленый
  </color>
  <material>
   Лен
  </material>
  <price>
   880630
  </price>
  <rating>
   1.34
  </rating>
  <reviews>
   613176
  </reviews>
 </clothing>
 <clothing>
  <id>
   683064649
  </id>
  <name>
   Ellesse Blouse L-3393
  </name>
  <category>
   Blouse
  </category>
  <size>
   XL
  </size>
  <color>
   Синий
  </color>
  <material>
   Кожа
  </material>
  <price>
   658050
  </price>
  <rating>
   2.47
  </rating>
  <reviews>
   157631
  </reviews>
  <sporty>
   yes
  </sporty>
 </clothing>
 <clothing>
  <id>
   998493511
  </id>
  <name>
   Vans Pants M-5627
  </name>
  <category>
   Pants
  </category>
  <size>
   XXL
  </size>
  <color>
   Красный
  </color>
  <material>
   Полиэстер
  </material>
  <price>
   996636
  </price>
  <rating>
   1.69
  </rating>
  <reviews>
   641504
  </reviews>
  <new>
   +
  </new>
  <sporty>
   no
  </sporty>
 </clothing>
 <clothing>
  <id>
   918630129
  </id>
  <name>
   New Balance Hat S-9184
  </name>
  <category>
   Hat
  </category>
  <size>
   L
  </size>
  <color>
   Желтый
  </color>
  <material>
   Полиэстер
  </material>
  <price>
   208002
  </price>
  <rating>
   4.09
  </rating>
  <reviews>
   394550
  </reviews>
  <new>
   -
  </new>
  <exclusive>
   no
  </exclusive>
 </clothing>
 <clothing>
  <id>
   623062506
  </id>
  <name>
   Under Armour Belts M-9154
  </name>
  <category>
   Belts
  </category>
  <size>
   M
  </size>
  <color>
   Оранжевый
  </color>
  <material>
   Кожа
  </material>
  <price>
   718952
  </price>
  <rating>
   3.91
  </rating>
  <reviews>
   392197
  </reviews>
  <new>
   -
  </new>
 </clothing>
 <clothing>
  <id>
   230393786
  </id>
  <name>
   Converse Hat Z-2815
  </name>
  <category>
   Hat
  </category>
  <size>
   L
  </size>
  <color>
   Зеленый
  </color>
  <material>
   Нейлон
  </material>
  <price>
   848606
  </price>
  <rating>
   1.36
  </rating>
  <reviews>
   932061
  </reviews>
  <sporty>
   no
  </sporty>
 </clothing>
</clothing-items>
