<?xml version="1.0" encoding="utf-8"?>
<clothing-items>
 <clothing>
  <id>
   266950853
  </id>
  <name>
   Fila Dress N-3624
  </name>
  <category>
   Dress
  </category>
  <size>
   M
  </size>
  <color>
   Зеленый
  </color>
  <material>
   Кожа
  </material>
  <price>
   793588
  </price>
  <rating>
   1.6
  </rating>
  <reviews>
   245961
  </reviews>
  <exclusive>
   no
  </exclusive>
 </clothing>
 <clothing>
  <id>
   281509450
  </id>
  <name>
   Converse Shoes W-5837
  </name>
  <category>
   Shoes
  </category>
  <size>
   S
  </size>
  <color>
   Зеленый
  </color>
  <material>
   Шерсть
  </material>
  <price>
   320707
  </price>
  <rating>
   3.69
  </rating>
  <reviews>
   554947
  </reviews>
  <sporty>
   no
  </sporty>
 </clothing>
 <clothing>
  <id>
   125159591
  </id>
  <name>
   Lacoste Skirt O-1071
  </name>
  <category>
   Skirt
  </category>
  <size>
   XL
  </size>
  <color>
   Желтый
  </color>
  <material>
   Шелк
  </material>
  <price>
   116223
  </price>
  <rating>
   2.84
  </rating>
  <reviews>
   893822
  </reviews>
  <new>
   -
  </new>
  <sporty>
   no
  </sporty>
 </clothing>
 <clothing>
  <id>
   955323855
  </id>
  <name>
   Adidas T-shirt Y-5564
  </name>
  <category>
   T-shirt
  </category>
  <size>
   S
  </size>
  <color>
   Оранжевый
  </color>
  <material>
   Шерсть
  </material>
  <price>
   182451
  </price>
  <rating>
   1.74
  </rating>
  <reviews>
   186964
  </reviews>
  <new>
   +
  </new>
  <exclusive>
   yes
  </exclusive>
  <sporty>
   no
  </sporty>
 </clothing>
 <clothing>
  <id>
   140169169
  </id>
  <name>
   Lacoste Sweater U-6479
  </name>
  <category>
   Sweater
  </category>
  <size>
   S
  </size>
  <color>
   Фиолетовый
  </color>
  <material>
   Шерсть
  </material>
  <price>
   677285
  </price>
  <rating>
   1.8
  </rating>
  <reviews>
   664785
  </reviews>
  <new>
   +
  </new>
  <exclusive>
   yes
  </exclusive>
  <sporty>
   no
  </sporty>
 </clothing>
 <clothing>
  <id>
   188980642
  </id>
  <name>
   Addidas Handbags L-8762
  </name>
  <category>
   Handbags
  </category>
  <size>
   XXL
  </size>
  <color>
   Голубой
  </color>
  <material>
   Шелк
  </material>
  <price>
   178798
  </price>
  <rating>
   3.97
  </rating>
  <reviews>
   802685
  </reviews>
  <exclusive>
   yes
  </exclusive>
  <sporty>
   yes
  </sporty>
 </clothing>
 <clothing>
  <id>
   367205479
  </id>
  <name>
   Puma Sweater O-2268
  </name>
  <category>
   Sweater
  </category>
  <size>
   XXL
  </size>
  <color>
   Красный
  </color>
  <material>
   Шерсть
  </material>
  <price>
   197746
  </price>
  <rating>
   2.23
  </rating>
  <reviews>
   75101
  </reviews>
  <exclusive>
   yes
  </exclusive>
  <sporty>
   no
  </sporty>
 </clothing>
 <clothing>
  <id>
   891080930
  </id>
  <name>
   Ellesse Shoes S-6156
  </name>
  <category>
   Shoes
  </category>
  <size>
   M
  </size>
  <color>
   Синий
  </color>
  <material>
   Полиэстер
  </material>
  <price>
   551582
  </price>
  <rating>
   3.05
  </rating>
  <reviews>
   927131
  </reviews>
  <new>
   -
  </new>
  <sporty>
   no
  </sporty>
 </clothing>
 <clothing>
  <id>
   982567729
  </id>
  <name>
   Under Armour Shirt Y-5109
  </name>
  <category>
   Shirt
  </category>
  <size>
   S
  </size>
  <color>
   Желтый
  </color>
  <material>
   Лен
  </material>
  <price>
   600371
  </price>
  <rating>
   3.9
  </rating>
  <reviews>
   209844
  </reviews>
 </clothing>
 <clothing>
  <id>
   128985028
  </id>
  <name>
   DC Jacket Z-2767
  </name>
  <category>
   Jacket
  </category>
  <size>
   XL
  </size>
  <color>
   Голубой
  </color>
  <material>
   Шерсть
  </material>
  <price>
   333215
  </price>
  <rating>
   2.11
  </rating>
  <reviews>
   97735
  </reviews>
  <new>
   +
  </new>
  <exclusive>
   no
  </exclusive>
  <sporty>
   no
  </sporty>
 </clothing>
 <clothing>
  <id>
   656175598
  </id>
  <name>
   Adidas Blouse E-4589
  </name>
  <category>
   Blouse
  </category>
  <size>
   M
  </size>
  <color>
   Синий
  </color>
  <material>
   Кожа
  </material>
  <price>
   857767
  </price>
  <rating>
   2.02
  </rating>
  <reviews>
   359225
  </reviews>
  <new>
   -
  </new>
 </clothing>
</clothing-items>
